{
    "fields": {
        "id": "increments",
        "title": "string:200|index",
        "excerpt": "text",
        "slug": "string:200|index",
        "content": "text"
        
    },
    "grid": [
        "title",
        "updated_at"
    ],
    "form": {
        "title": "text",
        "excerpt": "textarea",
        "slug": "slug:title",
        "content": "html"
    },
    "require": [
        "image",
        "user",
        "tags"
    ],
    "relations": {
        "meta": "hasOne:PostMeta,post_id,id"
    },
    "options": {
        "icon" : "fa-file-text-o",   
        "timestamps" : true,
        "status" : true,
        "per_page" : 20
    }

}